deeplite/deeplite-profiler.sig
deeplite/tf_profiler/tf_inference.cpython-38-x86_64-linux-gnu.so
deeplite/tf_profiler/tf_data_loader.cpython-38-x86_64-linux-gnu.so
deeplite/tf_profiler/tf_profiler.cpython-38-x86_64-linux-gnu.so
deeplite/profiler/evaluate.cpython-38-x86_64-linux-gnu.so
deeplite/profiler/data_loader.cpython-38-x86_64-linux-gnu.so
deeplite/profiler/formatter.cpython-38-x86_64-linux-gnu.so
deeplite/profiler/profiler.cpython-38-x86_64-linux-gnu.so
deeplite/profiler/__init__.cpython-38-x86_64-linux-gnu.so
deeplite/profiler/utils.cpython-38-x86_64-linux-gnu.so
deeplite/profiler/metrics.cpython-38-x86_64-linux-gnu.so
deeplite/torch_profiler/torch_data_loader.cpython-38-x86_64-linux-gnu.so
deeplite/torch_profiler/__init__.cpython-38-x86_64-linux-gnu.so
deeplite/torch_profiler/torch_profiler.cpython-38-x86_64-linux-gnu.so
deeplite/torch_profiler/torch_inference.cpython-38-x86_64-linux-gnu.so
examples/torch_example.py
examples/tf_example.py
deeplite_profiler-1.2.3.dist-info/METADATA
deeplite_profiler-1.2.3.dist-info/RECORD
deeplite_profiler-1.2.3.dist-info/top_level.txt
deeplite_profiler-1.2.3.dist-info/LICENSE
deeplite_profiler-1.2.3.dist-info/WHEEL
thirdparty/ptflops.py
