Metadata-Version: 2.1
Name: deeplite-profiler
Version: 1.2.3
Summary: Profiler for deep learning models
Home-page: https://github.com/Deeplite/deeplite-profiler
Author: Deeplite
Author-email: support@deeplite.ai
License: Apache 2.0
Keywords: profiler deep_neural_network deep_learning torch deeplite metrics
Platform: UNKNOWN
Classifier: Development Status :: 5 - Production/Stable
Classifier: Intended Audience :: Science/Research
Classifier: Intended Audience :: Developers
Classifier: Programming Language :: Python
Classifier: Programming Language :: Python :: 3.6
Classifier: Programming Language :: Python :: 3.7
Classifier: Programming Language :: Python :: 3.8
Classifier: Programming Language :: Python :: Implementation :: CPython
Classifier: Topic :: Scientific/Engineering :: Artificial Intelligence
Classifier: Topic :: Software Development :: Libraries :: Python Modules
Classifier: Operating System :: POSIX :: Linux
Classifier: Natural Language :: English
Classifier: License :: OSI Approved :: Apache Software License
Classifier: Environment :: Console
Requires-Dist: setuptools (<65.6.0)
Requires-Dist: numpy (>=1.17)
Provides-Extra: all
Requires-Dist: torch (<=1.8.1,>=1.4) ; extra == 'all'
Requires-Dist: ptflops (==0.6.2) ; extra == 'all'
Requires-Dist: protobuf (==3.19.*) ; extra == 'all'
Provides-Extra: all-gpu
Requires-Dist: torch (<=1.8.1,>=1.4) ; extra == 'all-gpu'
Requires-Dist: ptflops (==0.6.2) ; extra == 'all-gpu'
Requires-Dist: protobuf (==3.19.*) ; extra == 'all-gpu'
Requires-Dist: tensorflow-gpu (==1.14) ; (python_version <= "3.7.10") and extra == 'all-gpu'
Requires-Dist: tensorflow (==1.14) ; (python_version <= "3.7.10") and extra == 'all'
Provides-Extra: tf
Requires-Dist: protobuf (==3.19.*) ; extra == 'tf'
Provides-Extra: tf-gpu
Requires-Dist: protobuf (==3.19.*) ; extra == 'tf-gpu'
Requires-Dist: tensorflow-gpu (==1.14) ; (python_version <= "3.7.10") and extra == 'tf-gpu'
Requires-Dist: tensorflow (==1.14) ; (python_version <= "3.7.10") and extra == 'tf'
Provides-Extra: torch
Requires-Dist: torch (<=1.8.1,>=1.4) ; extra == 'torch'
Requires-Dist: ptflops (==0.6.2) ; extra == 'torch'
